xptcleaner/__init__.py
xptcleaner/__main__.py
xptcleaner/config.yaml
xptcleaner/xptclean.py
xptcleaner/cdisc_mapping/__init__.py
xptcleaner/cdisc_mapping/file_mapping/__init__.py
xptcleaner/cdisc_mapping/file_mapping/xpt_mapping.py
xptcleaner/cdisc_mapping/logger/__init__.py
xptcleaner/cdisc_mapping/logger/logger.py
xptcleaner/cdisc_mapping/utils/__init__.py
xptcleaner/cdisc_mapping/utils/utils.py
xptcleaner/cdisc_mapping/vocab_management/__init__.py
xptcleaner/cdisc_mapping/vocab_management/create_vocab.py
xptcleaner-1.0.0.dist-info/LICENSE
xptcleaner-1.0.0.dist-info/METADATA
xptcleaner-1.0.0.dist-info/WHEEL
xptcleaner-1.0.0.dist-info/entry_points.txt
xptcleaner-1.0.0.dist-info/top_level.txt
xptcleaner-1.0.0.dist-info/RECORD
