Metadata-Version: 2.1
Name: xptcleaner
Version: 1.0.0
Summary: CDISC SEND xpt (SAS v5 Transport format) files cleaner
Home-page: https://github.com/phuse-org/sendigR/tree/main/python/xptcleaner
Author: Cmsabbir Ahmed, Yousuf Ali, Susan Butler, Michael Denieu, William Houser, Brianna Paisley, Michael Rosentreter, Kevin Snyder, Wenxian Wang
Author-email: cmsabbir.ahmed@fda.hhs.gov, md.ali@fda.hhs.gov, susan.butler@fda.hhs.gov, michael.denieu@labcorp.com, william.houser@bms.com, paisley_brianna_meadow@lilly.com, michael.rosentreter@bayer.com, kevin.snyder@fda.hhs.gov, wenxian.wang@bms.com
License: # MIT License        
Classifier: License :: OSI Approved :: MIT License
Classifier: Programming Language :: Python
Classifier: Programming Language :: Python :: 3
License-File: LICENSE
Requires-Dist: pandas
Requires-Dist: pyreadstat
